Metadata-Version: 2.3
Name: square-database-structure
Version: 2.8.0
Summary: database scheme for my personal server.
Keywords: database,sqlalchemy,utilities
Author: Parth Mukesh Mangtani
Author-email: Parth Mukesh Mangtani <thepmsquare@gmail.com>
License: GPLv3
Classifier: Development Status :: 3 - Alpha
Classifier: Intended Audience :: Developers
Classifier: License :: OSI Approved :: GNU General Public License v3 (GPLv3)
Classifier: Operating System :: OS Independent
Classifier: Programming Language :: Python :: 3
Classifier: Programming Language :: Python :: 3.12
Classifier: Programming Language :: Python :: 3 :: Only
Classifier: Topic :: Database
Classifier: Topic :: Software Development :: Libraries :: Python Modules
Requires-Dist: sqlalchemy>=2.0.23
Requires-Dist: psycopg2-binary>=2.9.9
Requires-Dist: pytest>=8.0.0 ; extra == 'all'
Requires-Dist: pytest>=8.0.0 ; extra == 'test'
Requires-Python: >=3.12
Project-URL: homepage, https://github.com/thepmsquare/square_database_structure
Provides-Extra: all
Provides-Extra: test
